lab8part3/MUX81.v
`timescale 1ns/1ps
module MUX8to1(
    output wire [11:0]o,
    input wire [7:0][11:0]i,
    input wire [2:0]s
);

    wire [7:0][11:0]mins;
    wire [2:0] ns;
    not n0(ns[0],s[0]);
    not n1(ns[1],s[1]);
    not n2(ns[2],s[2]);
    wire [7:0] s1;
    and a0(s1[0],ns[0],ns[1],ns[2]);
    and a1(s1[1],s[0],ns[1],ns[2]);
    and a2(s1[2],ns[0],s[1],ns[2]);
    and a3(s1[3],s[0],s[1],ns[2]);
    and a4(s1[4],ns[0],ns[1],s[2]);
    and a5(s1[5],s[0],ns[1],s[2]);
    and a6(s1[6],ns[0],s[1],s[2]);
    and a7(s1[7],s[0],s[1],s[2]);

and aa10(mins[0][0],s1[0],i[0][0]);
and aa11(mins[0][1],s1[0],i[0][1]);
and aa12(mins[0][2],s1[0],i[0][2]);
and aa13(mins[0][3],s1[0],i[0][3]);
and aa14(mins[0][4],s1[0],i[0][4]);
and aa15(mins[0][5],s1[0],i[0][5]);
and aa16(mins[0][6],s1[0],i[0][6]);
and aa17(mins[0][7],s1[0],i[0][7]);
and aa018(mins[0][8],s1[0],i[0][8]);
and aa019(mins[0][9],s1[0],i[0][9]);
and aa020(mins[0][10],s1[0],i[0][10]);
and aa021(mins[0][11],s1[0],i[0][11]);


and aa20(mins[1][0],s1[1],i[1][0]);
and aa21(mins[1][1],s1[1],i[1][1]);
and aa22(mins[1][2],s1[1],i[1][2]);
and aa23(mins[1][3],s1[1],i[1][3]);
and aa24(mins[1][4],s1[1],i[1][4]);
and aa25(mins[1][5],s1[1],i[1][5]);
and aa26(mins[1][6],s1[1],i[1][6]);
and aa27(mins[1][7],s1[1],i[1][7]);
and aa118(mins[1][8],s1[1],i[1][8]);
and aa119(mins[1][9],s1[1],i[1][9]);
and aa120(mins[1][10],s1[1],i[1][10]);
and aa121(mins[1][11],s1[1],i[1][11]);


and aa30(mins[2][0],s1[2],i[2][0]);
and aa31(mins[2][1],s1[2],i[2][1]);
and aa32(mins[2][2],s1[2],i[2][2]);
and aa33(mins[2][3],s1[2],i[2][3]);
and aa34(mins[2][4],s1[2],i[2][4]);
and aa35(mins[2][5],s1[2],i[2][5]);
and aa36(mins[2][6],s1[2],i[2][6]);
and aa37(mins[2][7],s1[2],i[2][7]);
and aa218(mins[2][8],s1[2],i[2][8]);
and aa219(mins[2][9],s1[2],i[2][9]);
and aa220(mins[2][10],s1[2],i[2][10]);
and aa221(mins[2][11],s1[2],i[2][11]);


and aa40(mins[3][0],s1[3],i[3][0]);
and aa41(mins[3][1],s1[3],i[3][1]);
and aa42(mins[3][2],s1[3],i[3][2]);
and aa43(mins[3][3],s1[3],i[3][3]);
and aa44(mins[3][4],s1[3],i[3][4]);
and aa45(mins[3][5],s1[3],i[3][5]);
and aa46(mins[3][6],s1[3],i[3][6]);
and aa47(mins[3][7],s1[3],i[3][7]);
and aa318(mins[3][8],s1[3],i[3][8]);
and aa319(mins[3][9],s1[3],i[3][9]);
and aa320(mins[3][10],s1[3],i[3][10]);
and aa321(mins[3][11],s1[3],i[3][11]);


and aa50(mins[4][0],s1[4],i[4][0]);
and aa51(mins[4][1],s1[4],i[4][1]);
and aa52(mins[4][2],s1[4],i[4][2]);
and aa53(mins[4][3],s1[4],i[4][3]);
and aa54(mins[4][4],s1[4],i[4][4]);
and aa55(mins[4][5],s1[4],i[4][5]);
and aa56(mins[4][6],s1[4],i[4][6]);
and aa57(mins[4][7],s1[4],i[4][7]);
and aa418(mins[4][8],s1[4],i[4][8]);
and aa419(mins[4][9],s1[4],i[4][9]);
and aa420(mins[4][10],s1[4],i[4][10]);
and aa421(mins[4][11],s1[4],i[4][11]);


and aa60(mins[5][0],s1[5],i[5][0]);
and aa61(mins[5][1],s1[5],i[5][1]);
and aa62(mins[5][2],s1[5],i[5][2]);
and aa63(mins[5][3],s1[5],i[5][3]);
and aa64(mins[5][4],s1[5],i[5][4]);
and aa65(mins[5][5],s1[5],i[5][5]);
and aa66(mins[5][6],s1[5],i[5][6]);
and aa67(mins[5][7],s1[5],i[5][7]);
and aa518(mins[5][8],s1[5],i[5][8]);
and aa519(mins[5][9],s1[5],i[5][9]);
and aa520(mins[5][10],s1[5],i[5][10]);
and aa521(mins[5][11],s1[5],i[5][11]);


and aa70(mins[6][0],s1[6],i[6][0]);
and aa71(mins[6][1],s1[6],i[6][1]);
and aa72(mins[6][2],s1[6],i[6][2]);
and aa73(mins[6][3],s1[6],i[6][3]);
and aa74(mins[6][4],s1[6],i[6][4]);
and aa75(mins[6][5],s1[6],i[6][5]);
and aa76(mins[6][6],s1[6],i[6][6]);
and aa77(mins[6][7],s1[6],i[6][7]);
and aa618(mins[6][8],s1[6],i[6][8]);
and aa619(mins[6][9],s1[6],i[6][9]);
and aa620(mins[6][10],s1[6],i[6][10]);
and aa621(mins[6][11],s1[6],i[6][11]);


and aa80(mins[7][0],s1[7],i[7][0]);
and aa81(mins[7][1],s1[7],i[7][1]);
and aa82(mins[7][2],s1[7],i[7][2]);
and aa83(mins[7][3],s1[7],i[7][3]);
and aa84(mins[7][4],s1[7],i[7][4]);
and aa85(mins[7][5],s1[7],i[7][5]);
and aa86(mins[7][6],s1[7],i[7][6]);
and aa87(mins[7][7],s1[7],i[7][7]);
and aa718(mins[7][8],s1[7],i[7][8]);
and aa719(mins[7][9],s1[7],i[7][9]);
and aa720(mins[7][10],s1[7],i[7][10]);
and aa721(mins[7][11],s1[7],i[7][11]);

or op0(o[0],mins[0][0],mins[1][0],mins[2][0],mins[3][0],mins[4][0],mins[5][0],mins[6][0],mins[7][0]);
or op1(o[1],mins[0][1],mins[1][1],mins[2][1],mins[3][1],mins[4][1],mins[5][1],mins[6][1],mins[7][1]);
or op2(o[2],mins[0][2],mins[1][2],mins[2][2],mins[3][2],mins[4][2],mins[5][2],mins[6][2],mins[7][2]);
or op3(o[3],mins[0][3],mins[1][3],mins[2][3],mins[3][3],mins[4][3],mins[5][3],mins[6][3],mins[7][3]);
or op4(o[4],mins[0][4],mins[1][4],mins[2][4],mins[3][4],mins[4][4],mins[5][4],mins[6][4],mins[7][4]);
or op5(o[5],mins[0][5],mins[1][5],mins[2][5],mins[3][5],mins[4][5],mins[5][5],mins[6][5],mins[7][5]);
or op6(o[6],mins[0][6],mins[1][6],mins[2][6],mins[3][6],mins[4][6],mins[5][6],mins[6][6],mins[7][6]);
or op7(o[7],mins[0][7],mins[1][7],mins[2][7],mins[3][7],mins[4][7],mins[5][7],mins[6][7],mins[7][7]);
or op8(o[8],mins[0][8],mins[1][8],mins[2][8],mins[3][8],mins[4][8],mins[5][8],mins[6][8],mins[7][8]);
or op9(o[9],mins[0][9],mins[1][9],mins[2][9],mins[3][9],mins[4][9],mins[5][9],mins[6][9],mins[7][9]);
or op10(o[10],mins[0][10],mins[1][10],mins[2][10],mins[3][10],mins[4][10],mins[5][10],mins[6][10],mins[7][10]);
or op11(o[11],mins[0][11],mins[1][11],mins[2][11],mins[3][11],mins[4][11],mins[5][11],mins[6][11],mins[7][11]);

endmodule

lab8part12/registermod.v
`timescale 1ns/1ps
module regmod(
    output [11:0] out1,
    output [11:0] out2,
    input  [2:0] read1,
    input  [2:0] read2,
    input  [11:0] writeinp,
    input  enable,
    input  [2:0] s,
    input clk    
);
// reg [11:0] r0;
// reg [11:0] r1;
// reg [11:0] r2;
// reg [11:0] r3;
// reg [11:0] r4;
// reg [11:0] r5;
// reg [11:0] r6;
// reg [11:0] r7;
reg [7:0][11:0] r;
// r[0]=12'b000000000000;
// r[1]=12'b000000000000;
// r[2]=12'b000000000000;
// r[3]=12'b000000000000;
// r[4]=12'b000000000000;
// r[5]=12'b000000000000;
// r[6]=12'b000000000000;
// r[7]=12'b000000000000;
    wire [7:0] s1;
    wire [2:0] ns;
    not n0(ns[0],s[0]);
    not n1(ns[1],s[1]);
    not n2(ns[2],s[2]);
    and a0(s1[0],ns[0],ns[1],ns[2],clk,enable);
    and a1(s1[1],s[0],ns[1],ns[2],clk,enable);
    and a2(s1[2],ns[0],s[1],ns[2],clk,enable);
    and a3(s1[3],s[0],s[1],ns[2],clk,enable);
    and a4(s1[4],ns[0],ns[1],s[2],clk,enable);
    and a5(s1[5],s[0],ns[1],s[2],clk,enable);
    and a6(s1[6],ns[0],s[1],s[2],clk,enable);
    and a7(s1[7],s[0],s[1],s[2],clk,enable);
always @(posedge s1[0]) begin
  r[0] <= writeinp;
end
always @(posedge s1[1]) begin
  r[1] <= writeinp;
end
always @(posedge s1[2]) begin
  r[2] <= writeinp;
end
always @(posedge s1[3]) begin
  r[3] <= writeinp;
end
always @(posedge s1[4]) begin
  r[4] <= writeinp;
end
always @(posedge s1[5]) begin
  r[5] <= writeinp;
end
always @(posedge s1[6]) begin
  r[6] <= writeinp;
end
always @(posedge s1[7]) begin
  r[7] <= writeinp;
end
MUX8to1 m1(out1,r,read1);
MUX8to1 m2(out2,r,read2);






endmodule

lab8part3/part3_tb.v
`timescale 1ns/1ps

module regmod_tb;
    wire [11:0] out1;
    wire [11:0] out2;
    reg   [2:0] read1;
    reg   [2:0] read2;
    reg  [11:0] writeinp;
    reg   enable;
    reg   [2:0] s;
    reg clk;    
    regmod m1(out1,out2,read1,read2,writeinp,enable,s,clk);
always
       #1 clk = ~clk;
initial begin

$dumpfile("lab82_tb.vcd");
$dumpvars (0,regmod_tb);
clk=1'b0;

s=3'b000;enable=1'b1;read1=3'b000;read2=3'b001;writeinp=12'b111111111111;#10;
s=3'b011;enable=1'b1;read1=3'b000;read2=3'b011;writeinp=12'b111111111111;#10;



// opcode=3'b000;op1=12'b001110000001;op2=12'b001101000010;#10;
// opcode=3'b001;op1=12'b000000000011;op2=12'b000000000101;#10;
// opcode=3'b010;op1=12'b000000000011;op2=12'b000000000101;#10;
// opcode=3'b011;op1=12'b000000000011;op2=12'b000000000101;#10;
// opcode=3'b100;op1=12'b000000000011;op2=12'b000000000101;#10;
// opcode=3'b101;op1=12'b010011000000;op2=12'b010001000000;#10;
// opcode=3'b110;op1=12'b110001000000;op2=12'b110011000000;#10;
// opcode=3'b111;op1=12'b000000000011;op2=12'b000000000101;#10;
$display("Test completed");
#1000;$finish;

end

endmodule

lab8part3/lab82_tb.vcd
$date
	Thu Apr 13 17:30:35 2023
$end
$version
	Icarus Verilog
$end
$timescale
	1ps
$end
$scope module regmod_tb $end
$var wire 12 ! out2 [11:0] $end
$var wire 12 " out1 [11:0] $end
$var reg 1 # clk $end
$var reg 1 $ enable $end
$var reg 3 % read1 [2:0] $end
$var reg 3 & read2 [2:0] $end
$var reg 3 ' s [2:0] $end
$var reg 12 ( writeinp [11:0] $end
$scope module m1 $end
$var wire 1 # clk $end
$var wire 1 $ enable $end
$var wire 3 ) read1 [2:0] $end
$var wire 3 * read2 [2:0] $end
$var wire 3 + s [2:0] $end
$var wire 12 , writeinp [11:0] $end
$var wire 8 - s1 [7:0] $end
$var wire 12 . out2 [11:0] $end
$var wire 12 / out1 [11:0] $end
$var wire 3 0 ns [2:0] $end
$var reg 96 1 r [95:0] $end
$scope module m1 $end
$var wire 96 2 i [95:0] $end
$var wire 3 3 s [2:0] $end
$var wire 8 4 s1 [7:0] $end
$var wire 12 5 o [11:0] $end
$var wire 3 6 ns [2:0] $end
$var wire 96 7 mins [95:0] $end
$upscope $end
$scope module m2 $end
$var wire 96 8 i [95:0] $end
$var wire 3 9 s [2:0] $end
$var wire 8 : s1 [7:0] $end
$var wire 12 ; o [11:0] $end
$var wire 3 < ns [2:0] $end
$var wire 96 = mins [95:0] $end
$upscope $end
$upscope $end
$upscope $end
$enddefinitions $end
#0
$dumpvars
b0xxxxxxxxxxxx000000000000 =
b110 <
bx ;
b10 :
b1 9
bx 8
b0xxxxxxxxxxxx 7
b111 6
bx 5
b1 4
b0 3
bx 2
bx 1
b111 0
bx /
bx .
b0 -
b111111111111 ,
b0 +
b1 *
b0 )
b111111111111 (
b0 '
b1 &
b0 %
1$
0#
bx "
bx !
$end
#1000
b111111111111 "
b111111111111 /
b111111111111 5
b111111111111 7
bx111111111111 1
bx111111111111 2
bx111111111111 8
b1 -
1#
#2000
b0 -
0#
#3000
b1 -
1#
#4000
b0 -
0#
#5000
b1 -
1#
#6000
b0 -
0#
#7000
b1 -
1#
#8000
b0 -
0#
#9000
b1 -
1#
#10000
b0xxxxxxxxxxxx000000000000000000000000000000000000 =
b0 -
b100 <
b1000 :
b100 0
0#
b11 &
b11 *
b11 9
b11 '
b11 +
#11000
b111111111111 !
b111111111111 .
b111111111111 ;
b111111111111000000000000000000000000000000000000 =
bx111111111111xxxxxxxxxxxxxxxxxxxxxxxx111111111111 1
bx111111111111xxxxxxxxxxxxxxxxxxxxxxxx111111111111 2
bx111111111111xxxxxxxxxxxxxxxxxxxxxxxx111111111111 8
b1000 -
1#
#12000
b0 -
0#
#13000
b1000 -
1#
#14000
b0 -
0#
#15000
b1000 -
1#
#16000
b0 -
0#
#17000
b1000 -
1#
#18000
b0 -
0#
#19000
b1000 -
1#
#20000
b0 -
0#
#21000
b1000 -
1#
#22000
b0 -
0#
#23000
b1000 -
1#
#24000
b0 -
0#
#25000
b1000 -
1#
#26000
b0 -
0#
#27000
b1000 -
1#
#28000
b0 -
0#
#29000
b1000 -
1#
#30000
b0 -
0#
#31000
b1000 -
1#
#32000
b0 -
0#
#33000
b1000 -
1#
#34000
b0 -
0#
#35000
b1000 -
1#
#36000
b0 -
0#
#37000
b1000 -
1#
#38000
b0 -
0#
#39000
b1000 -
1#
#40000
b0 -
0#
#41000
b1000 -
1#
#42000
b0 -
0#
#43000
b1000 -
1#
#44000
b0 -
0#
#45000
b1000 -
1#
#46000
b0 -
0#
#47000
b1000 -
1#
#48000
b0 -
0#
#49000
b1000 -
1#
#50000
b0 -
0#
#51000
b1000 -
1#
#52000
b0 -
0#
#53000
b1000 -
1#
#54000
b0 -
0#
#55000
b1000 -
1#
#56000
b0 -
0#
#57000
b1000 -
1#
#58000
b0 -
0#
#59000
b1000 -
1#
#60000
b0 -
0#
#61000
b1000 -
1#
#62000
b0 -
0#
#63000
b1000 -
1#
#64000
b0 -
0#
#65000
b1000 -
1#
#66000
b0 -
0#
#67000
b1000 -
1#
#68000
b0 -
0#
#69000
b1000 -
1#
#70000
b0 -
0#
#71000
b1000 -
1#
#72000
b0 -
0#
#73000
b1000 -
1#
#74000
b0 -
0#
#75000
b1000 -
1#
#76000
b0 -
0#
#77000
b1000 -
1#
#78000
b0 -
0#
#79000
b1000 -
1#
#80000
b0 -
0#
#81000
b1000 -
1#
#82000
b0 -
0#
#83000
b1000 -
1#
#84000
b0 -
0#
#85000
b1000 -
1#
#86000
b0 -
0#
#87000
b1000 -
1#
#88000
b0 -
0#
#89000
b1000 -
1#
#90000
b0 -
0#
#91000
b1000 -
1#
#92000
b0 -
0#
#93000
b1000 -
1#
#94000
b0 -
0#
#95000
b1000 -
1#
#96000
b0 -
0#
#97000
b1000 -
1#
#98000
b0 -
0#
#99000
b1000 -
1#
#100000
b0 -
0#
#101000
b1000 -
1#
#102000
b0 -
0#
#103000
b1000 -
1#
#104000
b0 -
0#
#105000
b1000 -
1#
#106000
b0 -
0#
#107000
b1000 -
1#
#108000
b0 -
0#
#109000
b1000 -
1#
#110000
b0 -
0#
#111000
b1000 -
1#
#112000
b0 -
0#
#113000
b1000 -
1#
#114000
b0 -
0#
#115000
b1000 -
1#
#116000
b0 -
0#
#117000
b1000 -
1#
#118000
b0 -
0#
#119000
b1000 -
1#
#120000
b0 -
0#
#121000
b1000 -
1#
#122000
b0 -
0#
#123000
b1000 -
1#
#124000
b0 -
0#
#125000
b1000 -
1#
#126000
b0 -
0#
#127000
b1000 -
1#
#128000
b0 -
0#
#129000
b1000 -
1#
#130000
b0 -
0#
#131000
b1000 -
1#
#132000
b0 -
0#
#133000
b1000 -
1#
#134000
b0 -
0#
#135000
b1000 -
1#
#136000
b0 -
0#
#137000
b1000 -
1#
#138000
b0 -
0#
#139000
b1000 -
1#
#140000
b0 -
0#
#141000
b1000 -
1#
#142000
b0 -
0#
#143000
b1000 -
1#
#144000
b0 -
0#
#145000
b1000 -
1#
#146000
b0 -
0#
#147000
b1000 -
1#
#148000
b0 -
0#
#149000
b1000 -
1#
#150000
b0 -
0#
#151000
b1000 -
1#
#152000
b0 -
0#
#153000
b1000 -
1#
#154000
b0 -
0#
#155000
b1000 -
1#
#156000
b0 -
0#
#157000
b1000 -
1#
#158000
b0 -
0#
#159000
b1000 -
1#
#160000
b0 -
0#
#161000
b1000 -
1#
#162000
b0 -
0#
#163000
b1000 -
1#
#164000
b0 -
0#
#165000
b1000 -
1#
#166000
b0 -
0#
#167000
b1000 -
1#
#168000
b0 -
0#
#169000
b1000 -
1#
#170000
b0 -
0#
#171000
b1000 -
1#
#172000
b0 -
0#
#173000
b1000 -
1#
#174000
b0 -
0#
#175000
b1000 -
1#
#176000
b0 -
0#
#177000
b1000 -
1#
#178000
b0 -
0#
#179000
b1000 -
1#
#180000
b0 -
0#
#181000
b1000 -
1#
#182000
b0 -
0#
#183000
b1000 -
1#
#184000
b0 -
0#
#185000
b1000 -
1#
#186000
b0 -
0#
#187000
b1000 -
1#
#188000
b0 -
0#
#189000
b1000 -
1#
#190000
b0 -
0#
#191000
b1000 -
1#
#192000
b0 -
0#
#193000
b1000 -
1#
#194000
b0 -
0#
#195000
b1000 -
1#
#196000
b0 -
0#
#197000
b1000 -
1#
#198000
b0 -
0#
#199000
b1000 -
1#
#200000
b0 -
0#
#201000
b1000 -
1#
#202000
b0 -
0#
#203000
b1000 -
1#
#204000
b0 -
0#
#205000
b1000 -
1#
#206000
b0 -
0#
#207000
b1000 -
1#
#208000
b0 -
0#
#209000
b1000 -
1#
#210000
b0 -
0#
#211000
b1000 -
1#
#212000
b0 -
0#
#213000
b1000 -
1#
#214000
b0 -
0#
#215000
b1000 -
1#
#216000
b0 -
0#
#217000
b1000 -
1#
#218000
b0 -
0#
#219000
b1000 -
1#
#220000
b0 -
0#
#221000
b1000 -
1#
#222000
b0 -
0#
#223000
b1000 -
1#
#224000
b0 -
0#
#225000
b1000 -
1#
#226000
b0 -
0#
#227000
b1000 -
1#
#228000
b0 -
0#
#229000
b1000 -
1#
#230000
b0 -
0#
#231000
b1000 -
1#
#232000
b0 -
0#
#233000
b1000 -
1#
#234000
b0 -
0#
#235000
b1000 -
1#
#236000
b0 -
0#
#237000
b1000 -
1#
#238000
b0 -
0#
#239000
b1000 -
1#
#240000
b0 -
0#
#241000
b1000 -
1#
#242000
b0 -
0#
#243000
b1000 -
1#
#244000
b0 -
0#
#245000
b1000 -
1#
#246000
b0 -
0#
#247000
b1000 -
1#
#248000
b0 -
0#
#249000
b1000 -
1#
#250000
b0 -
0#
#251000
b1000 -
1#
#252000
b0 -
0#
#253000
b1000 -
1#
#254000
b0 -
0#
#255000
b1000 -
1#
#256000
b0 -
0#
#257000
b1000 -
1#
#258000
b0 -
0#
#259000
b1000 -
1#
#260000
b0 -
0#
#261000
b1000 -
1#
#262000
b0 -
0#
#263000
b1000 -
1#
#264000
b0 -
0#
#265000
b1000 -
1#
#266000
b0 -
0#
#267000
b1000 -
1#
#268000
b0 -
0#
#269000
b1000 -
1#
#270000
b0 -
0#
#271000
b1000 -
1#
#272000
b0 -
0#
#273000
b1000 -
1#
#274000
b0 -
0#
#275000
b1000 -
1#
#276000
b0 -
0#
#277000
b1000 -
1#
#278000
b0 -
0#
#279000
b1000 -
1#
#280000
b0 -
0#
#281000
b1000 -
1#
#282000
b0 -
0#
#283000
b1000 -
1#
#284000
b0 -
0#
#285000
b1000 -
1#
#286000
b0 -
0#
#287000
b1000 -
1#
#288000
b0 -
0#
#289000
b1000 -
1#
#290000
b0 -
0#
#291000
b1000 -
1#
#292000
b0 -
0#
#293000
b1000 -
1#
#294000
b0 -
0#
#295000
b1000 -
1#
#296000
b0 -
0#
#297000
b1000 -
1#
#298000
b0 -
0#
#299000
b1000 -
1#
#300000
b0 -
0#
#301000
b1000 -
1#
#302000
b0 -
0#
#303000
b1000 -
1#
#304000
b0 -
0#
#305000
b1000 -
1#
#306000
b0 -
0#
#307000
b1000 -
1#
#308000
b0 -
0#
#309000
b1000 -
1#
#310000
b0 -
0#
#311000
b1000 -
1#
#312000
b0 -
0#
#313000
b1000 -
1#
#314000
b0 -
0#
#315000
b1000 -
1#
#316000
b0 -
0#
#317000
b1000 -
1#
#318000
b0 -
0#
#319000
b1000 -
1#
#320000
b0 -
0#
#321000
b1000 -
1#
#322000
b0 -
0#
#323000
b1000 -
1#
#324000
b0 -
0#
#325000
b1000 -
1#
#326000
b0 -
0#
#327000
b1000 -
1#
#328000
b0 -
0#
#329000
b1000 -
1#
#330000
b0 -
0#
#331000
b1000 -
1#
#332000
b0 -
0#
#333000
b1000 -
1#
#334000
b0 -
0#
#335000
b1000 -
1#
#336000
b0 -
0#
#337000
b1000 -
1#
#338000
b0 -
0#
#339000
b1000 -
1#
#340000
b0 -
0#
#341000
b1000 -
1#
#342000
b0 -
0#
#343000
b1000 -
1#
#344000
b0 -
0#
#345000
b1000 -
1#
#346000
b0 -
0#
#347000
b1000 -
1#
#348000
b0 -
0#
#349000
b1000 -
1#
#350000
b0 -
0#
#351000
b1000 -
1#
#352000
b0 -
0#
#353000
b1000 -
1#
#354000
b0 -
0#
#355000
b1000 -
1#
#356000
b0 -
0#
#357000
b1000 -
1#
#358000
b0 -
0#
#359000
b1000 -
1#
#360000
b0 -
0#
#361000
b1000 -
1#
#362000
b0 -
0#
#363000
b1000 -
1#
#364000
b0 -
0#
#365000
b1000 -
1#
#366000
b0 -
0#
#367000
b1000 -
1#
#368000
b0 -
0#
#369000
b1000 -
1#
#370000
b0 -
0#
#371000
b1000 -
1#
#372000
b0 -
0#
#373000
b1000 -
1#
#374000
b0 -
0#
#375000
b1000 -
1#
#376000
b0 -
0#
#377000
b1000 -
1#
#378000
b0 -
0#
#379000
b1000 -
1#
#380000
b0 -
0#
#381000
b1000 -
1#
#382000
b0 -
0#
#383000
b1000 -
1#
#384000
b0 -
0#
#385000
b1000 -
1#
#386000
b0 -
0#
#387000
b1000 -
1#
#388000
b0 -
0#
#389000
b1000 -
1#
#390000
b0 -
0#
#391000
b1000 -
1#
#392000
b0 -
0#
#393000
b1000 -
1#
#394000
b0 -
0#
#395000
b1000 -
1#
#396000
b0 -
0#
#397000
b1000 -
1#
#398000
b0 -
0#
#399000
b1000 -
1#
#400000
b0 -
0#
#401000
b1000 -
1#
#402000
b0 -
0#
#403000
b1000 -
1#
#404000
b0 -
0#
#405000
b1000 -
1#
#406000
b0 -
0#
#407000
b1000 -
1#
#408000
b0 -
0#
#409000
b1000 -
1#
#410000
b0 -
0#
#411000
b1000 -
1#
#412000
b0 -
0#
#413000
b1000 -
1#
#414000
b0 -
0#
#415000
b1000 -
1#
#416000
b0 -
0#
#417000
b1000 -
1#
#418000
b0 -
0#
#419000
b1000 -
1#
#420000
b0 -
0#
#421000
b1000 -
1#
#422000
b0 -
0#
#423000
b1000 -
1#
#424000
b0 -
0#
#425000
b1000 -
1#
#426000
b0 -
0#
#427000
b1000 -
1#
#428000
b0 -
0#
#429000
b1000 -
1#
#430000
b0 -
0#
#431000
b1000 -
1#
#432000
b0 -
0#
#433000
b1000 -
1#
#434000
b0 -
0#
#435000
b1000 -
1#
#436000
b0 -
0#
#437000
b1000 -
1#
#438000
b0 -
0#
#439000
b1000 -
1#
#440000
b0 -
0#
#441000
b1000 -
1#
#442000
b0 -
0#
#443000
b1000 -
1#
#444000
b0 -
0#
#445000
b1000 -
1#
#446000
b0 -
0#
#447000
b1000 -
1#
#448000
b0 -
0#
#449000
b1000 -
1#
#450000
b0 -
0#
#451000
b1000 -
1#
#452000
b0 -
0#
#453000
b1000 -
1#
#454000
b0 -
0#
#455000
b1000 -
1#
#456000
b0 -
0#
#457000
b1000 -
1#
#458000
b0 -
0#
#459000
b1000 -
1#
#460000
b0 -
0#
#461000
b1000 -
1#
#462000
b0 -
0#
#463000
b1000 -
1#
#464000
b0 -
0#
#465000
b1000 -
1#
#466000
b0 -
0#
#467000
b1000 -
1#
#468000
b0 -
0#
#469000
b1000 -
1#
#470000
b0 -
0#
#471000
b1000 -
1#
#472000
b0 -
0#
#473000
b1000 -
1#
#474000
b0 -
0#
#475000
b1000 -
1#
#476000
b0 -
0#
#477000
b1000 -
1#
#478000
b0 -
0#
#479000
b1000 -
1#
#480000
b0 -
0#
#481000
b1000 -
1#
#482000
b0 -
0#
#483000
b1000 -
1#
#484000
b0 -
0#
#485000
b1000 -
1#
#486000
b0 -
0#
#487000
b1000 -
1#
#488000
b0 -
0#
#489000
b1000 -
1#
#490000
b0 -
0#
#491000
b1000 -
1#
#492000
b0 -
0#
#493000
b1000 -
1#
#494000
b0 -
0#
#495000
b1000 -
1#
#496000
b0 -
0#
#497000
b1000 -
1#
#498000
b0 -
0#
#499000
b1000 -
1#
#500000
b0 -
0#
#501000
b1000 -
1#
#502000
b0 -
0#
#503000
b1000 -
1#
#504000
b0 -
0#
#505000
b1000 -
1#
#506000
b0 -
0#
#507000
b1000 -
1#
#508000
b0 -
0#
#509000
b1000 -
1#
#510000
b0 -
0#
#511000
b1000 -
1#
#512000
b0 -
0#
#513000
b1000 -
1#
#514000
b0 -
0#
#515000
b1000 -
1#
#516000
b0 -
0#
#517000
b1000 -
1#
#518000
b0 -
0#
#519000
b1000 -
1#
#520000
b0 -
0#
#521000
b1000 -
1#
#522000
b0 -
0#
#523000
b1000 -
1#
#524000
b0 -
0#
#525000
b1000 -
1#
#526000
b0 -
0#
#527000
b1000 -
1#
#528000
b0 -
0#
#529000
b1000 -
1#
#530000
b0 -
0#
#531000
b1000 -
1#
#532000
b0 -
0#
#533000
b1000 -
1#
#534000
b0 -
0#
#535000
b1000 -
1#
#536000
b0 -
0#
#537000
b1000 -
1#
#538000
b0 -
0#
#539000
b1000 -
1#
#540000
b0 -
0#
#541000
b1000 -
1#
#542000
b0 -
0#
#543000
b1000 -
1#
#544000
b0 -
0#
#545000
b1000 -
1#
#546000
b0 -
0#
#547000
b1000 -
1#
#548000
b0 -
0#
#549000
b1000 -
1#
#550000
b0 -
0#
#551000
b1000 -
1#
#552000
b0 -
0#
#553000
b1000 -
1#
#554000
b0 -
0#
#555000
b1000 -
1#
#556000
b0 -
0#
#557000
b1000 -
1#
#558000
b0 -
0#
#559000
b1000 -
1#
#560000
b0 -
0#
#561000
b1000 -
1#
#562000
b0 -
0#
#563000
b1000 -
1#
#564000
b0 -
0#
#565000
b1000 -
1#
#566000
b0 -
0#
#567000
b1000 -
1#
#568000
b0 -
0#
#569000
b1000 -
1#
#570000
b0 -
0#
#571000
b1000 -
1#
#572000
b0 -
0#
#573000
b1000 -
1#
#574000
b0 -
0#
#575000
b1000 -
1#
#576000
b0 -
0#
#577000
b1000 -
1#
#578000
b0 -
0#
#579000
b1000 -
1#
#580000
b0 -
0#
#581000
b1000 -
1#
#582000
b0 -
0#
#583000
b1000 -
1#
#584000
b0 -
0#
#585000
b1000 -
1#
#586000
b0 -
0#
#587000
b1000 -
1#
#588000
b0 -
0#
#589000
b1000 -
1#
#590000
b0 -
0#
#591000
b1000 -
1#
#592000
b0 -
0#
#593000
b1000 -
1#
#594000
b0 -
0#
#595000
b1000 -
1#
#596000
b0 -
0#
#597000
b1000 -
1#
#598000
b0 -
0#
#599000
b1000 -
1#
#600000
b0 -
0#
#601000
b1000 -
1#
#602000
b0 -
0#
#603000
b1000 -
1#
#604000
b0 -
0#
#605000
b1000 -
1#
#606000
b0 -
0#
#607000
b1000 -
1#
#608000
b0 -
0#
#609000
b1000 -
1#
#610000
b0 -
0#
#611000
b1000 -
1#
#612000
b0 -
0#
#613000
b1000 -
1#
#614000
b0 -
0#
#615000
b1000 -
1#
#616000
b0 -
0#
#617000
b1000 -
1#
#618000
b0 -
0#
#619000
b1000 -
1#
#620000
b0 -
0#
#621000
b1000 -
1#
#622000
b0 -
0#
#623000
b1000 -
1#
#624000
b0 -
0#
#625000
b1000 -
1#
#626000
b0 -
0#
#627000
b1000 -
1#
#628000
b0 -
0#
#629000
b1000 -
1#
#630000
b0 -
0#
#631000
b1000 -
1#
#632000
b0 -
0#
#633000
b1000 -
1#
#634000
b0 -
0#
#635000
b1000 -
1#
#636000
b0 -
0#
#637000
b1000 -
1#
#638000
b0 -
0#
#639000
b1000 -
1#
#640000
b0 -
0#
#641000
b1000 -
1#
#642000
b0 -
0#
#643000
b1000 -
1#
#644000
b0 -
0#
#645000
b1000 -
1#
#646000
b0 -
0#
#647000
b1000 -
1#
#648000
b0 -
0#
#649000
b1000 -
1#
#650000
b0 -
0#
#651000
b1000 -
1#
#652000
b0 -
0#
#653000
b1000 -
1#
#654000
b0 -
0#
#655000
b1000 -
1#
#656000
b0 -
0#
#657000
b1000 -
1#
#658000
b0 -
0#
#659000
b1000 -
1#
#660000
b0 -
0#
#661000
b1000 -
1#
#662000
b0 -
0#
#663000
b1000 -
1#
#664000
b0 -
0#
#665000
b1000 -
1#
#666000
b0 -
0#
#667000
b1000 -
1#
#668000
b0 -
0#
#669000
b1000 -
1#
#670000
b0 -
0#
#671000
b1000 -
1#
#672000
b0 -
0#
#673000
b1000 -
1#
#674000
b0 -
0#
#675000
b1000 -
1#
#676000
b0 -
0#
#677000
b1000 -
1#
#678000
b0 -
0#
#679000
b1000 -
1#
#680000
b0 -
0#
#681000
b1000 -
1#
#682000
b0 -
0#
#683000
b1000 -
1#
#684000
b0 -
0#
#685000
b1000 -
1#
#686000
b0 -
0#
#687000
b1000 -
1#
#688000
b0 -
0#
#689000
b1000 -
1#
#690000
b0 -
0#
#691000
b1000 -
1#
#692000
b0 -
0#
#693000
b1000 -
1#
#694000
b0 -
0#
